{"_id": "56b859f238f0d87ed55e97d3", "slideshow_credits": null, "keywords": [], "source": "AP", "type_of_material": "News", "pub_date": "2016-02-08T04:00:20Z", "web_url": "http://www.nytimes.com/aponline/2016/02/08/sports/football/ap-fbn-super-bowl-the-manning-moment.html", "blog": [], "byline": {"organization": "THE ASSOCIATED PRESS", "person": [], "original": "By THE ASSOCIATED PRESS"}, "subsection_name": "Pro Football", "news_desk": "None", "document_type": "article", "word_count": "941", "print_page": null, "snippet": "Everyone got spoiled....", "section_name": "Sports", "lead_paragraph": "Everyone got spoiled.", "multimedia": [], "abstract": null, "headline": {"main": "Manning Spoils His Fans Again, Walks Off With a Second Title", "print_headline": "Manning Spoils His Fans Again, Walks Off With a Second Title"}}