{"commentSequence": 17102275, "userLocation": "San Miguel de Allende, Mexico", "userTitle": "NULL", "parentID": null, "sharing": 1, "userDisplayName": "dboss11", "status": "approved", "userURL": "NULL", "commentBody": "While Tom was winning Two S\u00faper Bowls with Eli, everything was okay. But then,  the front office provides him with little in the way of RB's, and he takes the brunt. He may not get that extra one year at the helm, but If the Mora's are serious about rebuilding the team, give TC what he needs, and by 2018, they will be in the Super Bowl again.", "createDate": "1451797168", "recommendations": 0, "updateDate": "1451841735", "commentTitle": "<br/>", "userID": 9496229, "picURL": "https://graphics8.nytimes.com/images/apps/timespeople/none.png", "depth": 1, "replies": [], "permID": "17102275", "recommendedFlag": null, "timespeople": 1, "reportAbuseFlag": null, "approveDate": "1451841735", "trusted": 0, "commentType": "comment", "parentUserDisplayName": null, "commentID": 17102275, "replyCount": 0, "editorsSelection": false}