{"commentSequence": 17211895, "userLocation": "Sacramento, CA", "userTitle": "NULL", "parentID": null, "sharing": 0, "userDisplayName": "105gene", "status": "approved", "userURL": "NULL", "commentBody": "Before the merger of the two leagues, the AFL was consistently derided by the NFL as a \"pass happy\" league that did not know how to play defense.", "createDate": "1452706305", "recommendations": 0, "updateDate": "1452708266", "commentTitle": "<br/>", "userID": 63720390, "picURL": "https://graphics8.nytimes.com/images/apps/timespeople/none.png", "depth": 1, "replies": [], "permID": "17211895", "recommendedFlag": null, "timespeople": 1, "reportAbuseFlag": null, "approveDate": "1452708266", "trusted": 0, "commentType": "comment", "parentUserDisplayName": null, "commentID": 17211895, "replyCount": 0, "editorsSelection": false}