{"commentSequence": 17225924, "userLocation": "taunton, mass.", "userTitle": "NULL", "parentID": null, "sharing": 0, "userDisplayName": "kjd", "status": "approved", "userURL": "NULL", "commentBody": "Check how many home games the Rams have sold out in the last six years!", "createDate": "1452801363", "recommendations": 0, "updateDate": "1452802594", "commentTitle": "<br/>", "userID": 31857736, "picURL": "https://graphics8.nytimes.com/images/apps/timespeople/none.png", "depth": 1, "replies": [], "permID": "17225924", "recommendedFlag": null, "timespeople": 1, "reportAbuseFlag": null, "approveDate": "1452802594", "trusted": 0, "commentType": "comment", "parentUserDisplayName": null, "commentID": 17225924, "replyCount": 0, "editorsSelection": false}