{"commentSequence": 17249259, "userLocation": "Cambridge, MA", "userTitle": "NULL", "parentID": null, "sharing": 0, "userDisplayName": "naif", "status": "approved", "userURL": "NULL", "commentBody": "Patriots won big as they deserved, a true class act, they are. It was their time again on the big stage, and they not only delivered, they shone. Folks, enjoy this time watching the dedicated best at work, and the marvelous legacy they have earned. They are one of the NFL's greatest and hardest-working franchises during this 15-year consistent period.", "createDate": "1453005563", "recommendations": 94, "updateDate": "1453006651", "commentTitle": "<br/>", "userID": 55873865, "picURL": "https://graphics8.nytimes.com/images/apps/timespeople/none.png", "depth": 1, "replies": [], "permID": "17249259", "recommendedFlag": null, "timespeople": 1, "reportAbuseFlag": null, "approveDate": "1453006651", "trusted": 0, "commentType": "comment", "parentUserDisplayName": null, "commentID": 17249259, "replyCount": 0, "editorsSelection": false}