{"commentSequence": 17257546, "userLocation": "lubbock", "userTitle": "NULL", "parentID": null, "sharing": 0, "userDisplayName": "Steve", "status": "approved", "userURL": "NULL", "commentBody": "Omaha? Does it ALWAYS have to be Omaha?", "createDate": "1453110688", "recommendations": 5, "updateDate": "1453128191", "commentTitle": "<br/>", "userID": 65431352, "picURL": "https://graphics8.nytimes.com/images/apps/timespeople/none.png", "depth": 1, "replies": [], "permID": "17257546", "recommendedFlag": null, "timespeople": 1, "reportAbuseFlag": null, "approveDate": "1453128191", "trusted": 0, "commentType": "comment", "parentUserDisplayName": null, "commentID": 17257546, "replyCount": 0, "editorsSelection": false}