{"commentSequence": 17262138, "userLocation": "west village, nyc", "userTitle": "NULL", "parentID": null, "sharing": 0, "userDisplayName": "rollie", "status": "approved", "userURL": "NULL", "commentBody": "I'm a Giants fan and a Jets fan, but I have to admit that I'm also a Patriots fan.  Sorry, but they are entertaining, and great. They're always there on top, year after year, and no one else is that consistent. Coach Belicose ( bellichick, sorry) has a career as a straight man in a comedy duo waiting for him should he ever choose to move on from the NFL", "createDate": "1453153231", "recommendations": 5, "updateDate": "1453157305", "commentTitle": "<br/>", "userID": 63360783, "picURL": "https://graphics8.nytimes.com/images/apps/timespeople/none.png", "depth": 1, "replies": [{"commentSequence": 17263196, "userLocation": "Nebraska", "userTitle": "NULL", "parentID": 17262138, "sharing": 0, "userDisplayName": "Jane", "status": "approved", "userURL": "NULL", "commentBody": "Plus BB is so cuddly", "createDate": "1453173864", "recommendations": 2, "updateDate": "1453219208", "commentTitle": "<br/>", "userID": 57381590, "picURL": "https://graphics8.nytimes.com/images/apps/timespeople/none.png", "depth": 2, "replies": [], "permID": "17262138:17263196", "recommendedFlag": null, "timespeople": 1, "reportAbuseFlag": null, "approveDate": "1453219208", "trusted": 0, "commentType": "userReply", "parentUserDisplayName": "rollie", "commentID": 17263196, "replyCount": 0, "editorsSelection": false}], "permID": "17262138", "recommendedFlag": null, "timespeople": 1, "reportAbuseFlag": null, "approveDate": "1453157305", "trusted": 0, "commentType": "comment", "parentUserDisplayName": null, "commentID": 17262138, "replyCount": 1, "editorsSelection": false}