{"commentSequence": 18325990, "userLocation": "New York, New York", "userTitle": "NULL", "parentID": 18324773, "sharing": 0, "userDisplayName": "JEG", "status": "approved", "userURL": "NULL", "commentBody": "Jeffrey, the very point of my previous comment is that at one time Brady could have adopted your argument while accepting punishment from the Commissioner.  In other words, keeping this within the confines of the league, while arguing his ultimate innocence in the court of public opinion.  Now, barring the unlikely reversal by the Second Circuit en banc, Brady is forever saddled with a federal appeals court opinion which undercuts many of his arguments, particularly about his reasons for destroying his cell phone and any evidence it contained.  Brady himself turned this from an issue of what can be scientifically proven about the pressure of the football used the AFC Championship game, and made it about his behavior of which there is no controversy.  In doing so, he lost.", "createDate": "1461606551", "recommendations": 38, "updateDate": "1461604999", "commentTitle": "<br/>", "userID": 18215173, "picURL": "https://s3.amazonaws.com/pimage.timespeople.nytimes.com/1821/5173/cropped-18215173.jpg?0.35560772055760026", "depth": 1, "replies": [], "permID": "18324773:18325990", "recommendedFlag": null, "timespeople": 1, "reportAbuseFlag": null, "approveDate": "1461608599", "trusted": 0, "commentType": "userReply", "parentUserDisplayName": "JEG", "commentID": 18325990, "replyCount": 0, "editorsSelection": true}