{"commentSequence": 20402561, "userLocation": "Chi", "userTitle": "NULL", "parentID": null, "sharing": 1, "userDisplayName": "Fhc", "status": "approved", "userURL": "NULL", "commentBody": "I can't tell how much of the coverage is ratings drama - but right now I'm trying to figure out where I'm going to move. If he wins, I just don't think I can take 4 years of this. Where are all these votes Hillary was supposed to get?", "createDate": "1478660828", "recommendations": 2, "updateDate": "1478661047", "commentTitle": "<br/>", "userID": 65377180, "picURL": "https://graphics8.nytimes.com/images/apps/timespeople/none.png", "depth": 1, "replies": [{"commentSequence": 20403908, "userLocation": "Illinois", "userTitle": "NULL", "parentID": 20402561, "sharing": 0, "userDisplayName": "Joseph Zrnchik", "status": "approved", "userURL": "NULL", "commentBody": "She came, she saw, she lost!", "createDate": "1478666870", "recommendations": 3, "updateDate": "1478690782", "commentTitle": "n/a", "userID": 63600523, "picURL": "https://graphics8.nytimes.com/images/apps/timespeople/none.png", "depth": 2, "replies": [], "permID": "20402561:20403908", "recommendedFlag": null, "timespeople": 1, "reportAbuseFlag": null, "approveDate": "1478690782", "trusted": 0, "commentType": "userReply", "parentUserDisplayName": "Fhc", "commentID": 20403908, "replyCount": 0, "editorsSelection": false}], "permID": "20402561", "recommendedFlag": null, "timespeople": 1, "reportAbuseFlag": null, "approveDate": "1478661047", "trusted": 0, "commentType": "comment", "parentUserDisplayName": null, "commentID": 20402561, "replyCount": 1, "editorsSelection": false}