{"commentSequence": 20070321, "userLocation": "Santa Monica, CA", "userTitle": "NULL", "parentID": null, "sharing": 0, "userDisplayName": "Tom Peterson", "status": "approved", "userURL": "NULL", "commentBody": "As a life long Cubs fan, I sometimes think, \"OMG what if we actually win the World Series!!?  What will we do then?  It would be like the end of history.\"  But I guess we could go in the other direction and become a dynasty.  Why not?", "createDate": "1475964612", "recommendations": 0, "updateDate": "1476110893", "commentTitle": "<br/>", "userID": 14631495, "picURL": "https://graphics8.nytimes.com/images/apps/timespeople/none.png", "depth": 1, "replies": [], "permID": "20070321", "recommendedFlag": null, "timespeople": 1, "reportAbuseFlag": null, "approveDate": "1476114493", "trusted": 0, "commentType": "comment", "parentUserDisplayName": null, "commentID": 20070321, "replyCount": 0, "editorsSelection": false}