{"_id": "579050a938f0d85ae5114a96", "slideshow_credits": null, "keywords": [], "source": "AP", "type_of_material": "News", "pub_date": "2016-07-21T00:31:25Z", "web_url": "http://www.nytimes.com/aponline/2016/07/21/us/ap-us-aaron-hernandez.html", "blog": [], "byline": {"organization": "THE ASSOCIATED PRESS", "person": [], "original": "By THE ASSOCIATED PRESS"}, "subsection_name": null, "news_desk": "None", "document_type": "article", "word_count": "133", "print_page": null, "snippet": "Former New England Patriots star Aaron Hernandez has a new legal team to defend him in the 2012 slayings of two men outside a Boston nightclub....", "section_name": "U.S.", "lead_paragraph": "Former New England Patriots star Aaron Hernandez has a new legal team to defend him in the 2012 slayings of two men outside a Boston nightclub.", "multimedia": [], "abstract": null, "headline": {"main": "New Legal Team Granted for Ex-NFL Star Aaron Hernandez", "print_headline": "New Legal Team Granted for Ex-NFL Star Aaron Hernandez"}}