{"_id": "56941e9938f0d80745b73502", "slideshow_credits": null, "keywords": [], "source": "AP", "type_of_material": "News", "pub_date": "2016-01-11T14:13:28Z", "web_url": "http://www.nytimes.com/aponline/2016/01/11/sports/football/ap-fbn-lions-quinn.html", "blog": [], "byline": {"organization": "THE ASSOCIATED PRESS", "person": [], "original": "By THE ASSOCIATED PRESS"}, "subsection_name": "Pro Football", "news_desk": "None", "document_type": "article", "word_count": "114", "print_page": null, "snippet": "Detroit Lions general manager Bob Quinn says he has not decided whether to retain or fire coach Jim Caldwell....", "section_name": "Sports", "lead_paragraph": "Detroit Lions general manager Bob Quinn says he has not decided whether to retain or fire coach Jim Caldwell.", "multimedia": [], "abstract": null, "headline": {"main": "Lions GM Bob Quinn Undecided on Coach Jim Caldwell's Future", "print_headline": "Lions GM Bob Quinn Undecided on Coach Jim Caldwell's Future"}}