{"_id": "569865ca38f0d8108a7eb84e", "slideshow_credits": null, "keywords": [], "source": "Reuters", "type_of_material": "News", "pub_date": "2016-01-14T22:18:17Z", "web_url": "http://www.nytimes.com/reuters/2016/01/14/sports/football/14reuters-nfl-coaches.html", "blog": [], "byline": {"organization": "REUTERS", "person": [], "original": "By REUTERS"}, "subsection_name": "Pro Football", "news_desk": "None", "document_type": "article", "word_count": "185", "print_page": null, "snippet": "Doug Pederson is to become the new head coach of the Philadelphia Eagles, various media outlets reported on Thursday, with the appointment unable to be officially announced until the Kansas City Chiefs lose in the playoffs....", "section_name": "Sports", "lead_paragraph": "Doug Pederson is to become the new head coach of the Philadelphia Eagles, various media outlets reported on Thursday, with the appointment unable to be officially announced until the Kansas City Chiefs lose in the playoffs.", "multimedia": [], "abstract": null, "headline": {"main": "Eagles Line Up Pederson as New Head Coach: Reports", "print_headline": "Eagles Line Up Pederson as New Head Coach: Reports"}}