{"_id": "5710682038f0d84d2c0d7752", "slideshow_credits": null, "keywords": [], "source": "AP", "type_of_material": "News", "pub_date": "2016-04-15T00:01:33Z", "web_url": "http://www.nytimes.com/aponline/2016/04/15/us/ap-history.html", "blog": [], "byline": {"organization": "THE ASSOCIATED PRESS", "person": [], "original": "By THE ASSOCIATED PRESS"}, "subsection_name": null, "news_desk": "None", "document_type": "article", "word_count": "818", "print_page": null, "snippet": "Today in History...", "section_name": "U.S.", "lead_paragraph": "Today in History", "multimedia": [], "abstract": null, "headline": {"main": "Today in History", "print_headline": "Today in History"}}