{"_id": "5733575738f0d857ffcae5dc", "slideshow_credits": null, "keywords": [], "source": "AP", "type_of_material": "News", "pub_date": "2016-05-11T11:58:58Z", "web_url": "http://www.nytimes.com/aponline/2016/05/11/us/politics/ap-us-congress-fantasy-sports.html", "blog": [], "byline": {"organization": "THE ASSOCIATED PRESS", "person": [], "original": "By THE ASSOCIATED PRESS"}, "subsection_name": "Politics", "news_desk": "None", "document_type": "article", "word_count": "590", "print_page": null, "snippet": "Congress on Wednesday launched a fact-finding mission into the loosely regulated world of fantasy sports games &#8212; a multibillion-dollar business that seemingly advertised everywhere during the pro football season....", "section_name": "U.S.", "lead_paragraph": "Congress on Wednesday launched a fact-finding mission into the loosely regulated world of fantasy sports games &#8212; a multibillion-dollar business that seemingly advertised everywhere during the pro football season.", "multimedia": [], "abstract": null, "headline": {"main": "Congress Putting Daily Fantasy Sports Games Under Scrutiny", "print_headline": "Congress Putting Daily Fantasy Sports Games Under Scrutiny"}}